qv_download_harshal499/QV_Download_v6.py
qv_download_harshal499/__init__.py
qv_download_harshal499-0.0.2.dist-info/LICENSE
qv_download_harshal499-0.0.2.dist-info/METADATA
qv_download_harshal499-0.0.2.dist-info/WHEEL
qv_download_harshal499-0.0.2.dist-info/top_level.txt
qv_download_harshal499-0.0.2.dist-info/RECORD
