Metadata-Version: 2.1
Name: qv_download_harshal499
Version: 0.0.2
Summary: A package to automate downloading from QV & ER for HC
Author-email: Harshal Sarode <hsarode04@gmail.com>
Classifier: Programming Language :: Python :: 3
Classifier: License :: OSI Approved :: MIT License
Classifier: Operating System :: OS Independent
Requires-Python: >=3.8
License-File: LICENSE
Requires-Dist: rsa
Requires-Dist: getpass
Requires-Dist: pandas
Requires-Dist: pywin32
Requires-Dist: selenium
